CO_Lab_1/code/MUX_2to1.v
//Subject:     CO project 1 - MUX 221
//--------------------------------------------------------------------------------
//Version:     1
//--------------------------------------------------------------------------------
//Writer:      Yu-Chen Hsiao
//----------------------------------------------
//Date:         2018/7/19
//----------------------------------------------
//Description:  Multiplexer
//--------------------------------------------------------------------------------

module MUX_2to1(data0_i, data1_i, select_i, data_o);

  parameter size = 0;

  //I/O ports
  input   [size-1:0] data0_i;
  input   [size-1:0] data1_i;
  input              select_i;
  output  [size-1:0] data_o;

  //Internal Signals
  wire    data0_i;
  wire    data1_i;
  wire    select_i;
  wire    data_o;

  //Main function
  assign data_o = (select_i == 0) ? data0_i : data1_i;

endmodule

CO_Lab_1/code/Shift_Left_Two_32.v
//Subject:      CO project 1 - Shift_Left_Two_32
//--------------------------------------------------------------------------------
//Version:     1
//--------------------------------------------------------------------------------
//Description: 
//--------------------------------------------------------------------------------

module Shift_Left_Two_32(
    data_i,
    data_o
    );

//I/O ports                    
input [32-1:0] data_i;
output [32-1:0] data_o;

//shift left 2
     
endmodule

CO_Lab_1/code/Adder.v
//Description:Adder Operation
//--------------------------------------------------------------------------------

module Adder(src1_i, src2_i, sum_o);
  //I/O ports
  input  [32-1:0]  src1_i;
  input  [32-1:0]	 src2_i;
  output [32-1:0]	 sum_o;

  //Internal Signals
  wire   [32-1:0]	 sum_o;

  //Main function
  assign sum_o = src1_i + src2_i;
endmodule

CO_Lab_1/code/ALU.v
module ALU( src1_i, src2_i, ctrl_i, result_o, zero_o );

//I/O ports
input  [32-1:0]  src1_i;
input  [32-1:0]	 src2_i;
input  [4-1:0]   ctrl_i;

output [32-1:0]	 result_o;
output           zero_o;

//Internal signals
reg    [32-1:0]  result_o;
wire             zero_o;

//Parameter

//Main function

endmodule

CO_Lab_1/code/Sign_Extend.v
//Subject:     CO project 1 - Sign extend
//--------------------------------------------------------------------------------
//Version:     1
//--------------------------------------------------------------------------------
//Writer:       Yu-Chien Hsiao
//----------------------------------------------
//Date:         2018/7/19
//----------------------------------------------
//Description:  finish
//--------------------------------------------------------------------------------

module Sign_Extend(
    data_i,
    data_o
    );

//I/O ports
input   [16-1:0] data_i;
output  [32-1:0] data_o;

//Internal Signals
reg     [32-1:0] data_o;

//Sign extended
always @ (data_i) begin
  data_o[16-1:0] = data_i;
  data_o[32-1:16] = {16{data_i[16-1]}};
end

endmodule

CO_Lab_1/code/ALU_Ctrl.v
module ALU_Ctrl( funct_i, ALUOp_i, ALUCtrl_o );

//I/O ports
input      [6-1:0] funct_i;
input      [3-1:0] ALUOp_i;

output     [4-1:0] ALUCtrl_o;

//Internal Signals
reg        [4-1:0] ALUCtrl_o;

//Parameter

//Select exact operation

endmodule

CO_Lab_1/code/Decoder.v
//Subject:     CO project 1 - Decoder
//--------------------------------------------------------------------------------
//Version:     1
//--------------------------------------------------------------------------------
//Writer:      
//----------------------------------------------
//Date:        
//----------------------------------------------
//Description: 
//--------------------------------------------------------------------------------

module Decoder(
    instr_op_i,
	RegWrite_o,
	ALU_op_o,
	ALUSrc_o,
	RegDst_o,
	Branch_o
	);
     
//I/O ports
input  [6-1:0] instr_op_i;

output         RegWrite_o;
output [3-1:0] ALU_op_o;
output         ALUSrc_o;
output         RegDst_o;
output         Branch_o;
 
//Internal Signals
reg    [3-1:0] ALU_op_o;
reg            ALUSrc_o;
reg            RegWrite_o;
reg            RegDst_o;
reg            Branch_o;

//Parameter


//Main function

endmodule

CO_Lab_1/code/Reg_File.v
//Subject:     CO project 1 - Register File
//--------------------------------------------------------------------------------
//Version:     1
//--------------------------------------------------------------------------------
//Writer:      
//----------------------------------------------
//Date:        
//----------------------------------------------
//Description: 
//--------------------------------------------------------------------------------
module Reg_File(
    clk_i,
	rst_i,
    RSaddr_i,
    RTaddr_i,
    RDaddr_i,
    RDdata_i,
    RegWrite_i,
    RSdata_o,
    RTdata_o
    );
          
//I/O ports
input           clk_i;
input           rst_i;
input           RegWrite_i;
input  [5-1:0]  RSaddr_i;
input  [5-1:0]  RTaddr_i;
input  [5-1:0]  RDaddr_i;
input  [32-1:0] RDdata_i;

output [32-1:0] RSdata_o;
output [32-1:0] RTdata_o;   

//Internal signals/registers           
reg  signed [32-1:0] Reg_File [0:32-1];     //32 word registers
wire        [32-1:0] RSdata_o;
wire        [32-1:0] RTdata_o;

//Read the data
assign RSdata_o = Reg_File[RSaddr_i] ;
assign RTdata_o = Reg_File[RTaddr_i] ;   

//Writing data when postive edge clk_i and RegWrite_i was set.
always @( posedge rst_i or posedge clk_i  ) begin
    if(rst_i == 0) begin
	    Reg_File[0]  <= 0; Reg_File[1]  <= 0; Reg_File[2]  <= 0; Reg_File[3]  <= 0;
	    Reg_File[4]  <= 0; Reg_File[5]  <= 0; Reg_File[6]  <= 0; Reg_File[7]  <= 0;
        Reg_File[8]  <= 0; Reg_File[9]  <= 0; Reg_File[10] <= 0; Reg_File[11] <= 0;
	    Reg_File[12] <= 0; Reg_File[13] <= 0; Reg_File[14] <= 0; Reg_File[15] <= 0;
        Reg_File[16] <= 0; Reg_File[17] <= 0; Reg_File[18] <= 0; Reg_File[19] <= 0;      
        Reg_File[20] <= 0; Reg_File[21] <= 0; Reg_File[22] <= 0; Reg_File[23] <= 0;
        Reg_File[24] <= 0; Reg_File[25] <= 0; Reg_File[26] <= 0; Reg_File[27] <= 0;
        Reg_File[28] <= 0; Reg_File[29] <= 0; Reg_File[30] <= 0; Reg_File[31] <= 0;
	end
    else begin
        if(RegWrite_i) 
            Reg_File[RDaddr_i] <= RDdata_i;	
		else 
		    Reg_File[RDaddr_i] <= Reg_File[RDaddr_i];
	end
end

endmodule

CO_Lab_1/code/Instr_Memory.v
//Description:Instruction Memory
//--------------------------------------------------------------------------------

module Instr_Memory(pc_addr_i, instr_o);

	//I/O ports
	input  [32-1:0]  pc_addr_i;
	output [32-1:0]	 instr_o;

	//Internal Signals
	reg    [32-1:0]	 instr_o;
	integer          i;

	//32 words Memory
	reg    [32-1:0]  Instr_Mem [0:32-1];

	//Parameter

	//Main function
	always @(pc_addr_i) begin
		instr_o = Instr_Mem[pc_addr_i/4];
	end

	//Initial Memory Contents
	initial begin
	    for ( i=0; i<32; i=i+1 )
		    Instr_Mem[i] = 32'b0;
	    $readmemb("CO_P1_test_data3.txt", Instr_Mem);  //Read instruction from "CO_P1_test_data1.txt"
	end
endmodule

CO_Lab_1/code/ProgramCounter.v
//Subject:     CO project 1 - PC
//--------------------------------------------------------------------------------
//Version:     1
//--------------------------------------------------------------------------------
//Writer:      
//----------------------------------------------
//Date:        
//----------------------------------------------
//Description: 
//--------------------------------------------------------------------------------

module ProgramCounter(
    clk_i,
	rst_i,
	pc_in_i,
	pc_out_o
	);
     
//I/O ports
input           clk_i;
input	        rst_i;
input  [32-1:0] pc_in_i;
output [32-1:0] pc_out_o;
 
//Internal Signals
reg    [32-1:0] pc_out_o;
 
//Parameter

    
//Main function
always @(posedge clk_i) begin
    if(~rst_i)
	    pc_out_o <= 0;
	else
	    pc_out_o <= pc_in_i;
end

endmodule

CO_Lab_1/code/Simple_Single_CPU.v
module Simple_Single_CPU( clk_i, rst_i );

//I/O port
input         clk_i;
input         rst_i;

//Internal Signles
wire [32-1:0] instruction, writeData, readData1, readData2, ALU_result, Shifter_result;
wire RegDst, RegWrite, ALUSrc;
wire [3-1:0] ALUOP;

//Greate componentes
ProgramCounter PC(
        .clk_i(),
        .rst_i (),
        .pc_in_i() ,
        .pc_out_o()
);

Adder Adder1(
        .src1_i(),
        .src2_i(),
        .sum_o()
);

Instr_Memory IM(
        .pc_addr_i(),
        .instr_o()
);

MUX_2to1 #(.size(5)) Mux_Write_Reg(
        .data0_i(),
        .data1_i(),
        .select_i(),
        .data_o()
);

Reg_File RF(
        .clk_i(),
        .rst_i() ,
        .RSaddr_i() ,
        .RTaddr_i() ,
        .RDaddr_i() ,
        .RDdata_i()  ,
        .RegWrite_i (),
        .RSdata_o() ,
        .RTdata_o()
);

Decoder Decoder(
        .instr_op_i(),
        .RegWrite_o(),
        .ALU_op_o(),
        .ALUSrc_o(),
        .RegDst_o(),
        .Branch_o()
);

ALU_Ctrl AC(
        .funct_i(),
        .ALUOp_i(),
        .ALUCtrl_o()
);

Sign_Extend SE(
        .data_i(),
        .data_o()
);

MUX_2to1 #(.size(32)) Mux_ALUSrc(
        .data0_i(),
        .data1_i(),
        .select_i(),
        .data_o()
);

ALU ALU(
        .src1_i(),
        .src2_i(),
        .ctrl_i(),
        .result_o(),
        .zero_o()
);

Adder Adder2(
        .src1_i(),
        .src2_i(),
        .sum_o()
);

Shift_Left_Two_32 Shifter(
        .data_i(),
        .data_o()
);

MUX_2to1 #(.size(32)) Mux_PC_Source(
        .data0_i(),
        .data1_i(),
        .select_i(),
        .data_o()
);

endmodule

CO_Lab_1/code/Test_Bench.v
//Description: TestBench
//--------------------------------------------------------------------------------

`define CYCLE_TIME 10
`define END_COUNT 25
module TestBench;

  //Internal Signals
  reg         CLK;
  reg         RST;
  integer     count;
  integer     handle;
  integer     end_count;
  //Greate tested modle
  Simple_Single_CPU cpu(
      .clk_i(CLK),
  		.rst_i(RST)
  		);

  //Main function

  always #(`CYCLE_TIME/2) CLK = ~CLK;

  initial  begin
  	$dumpfile("Single_Cycle_CPU.vcd");
  	$dumpvars;

    handle = $fopen("CO_P1_Result.txt");
  	CLK = 0;
    RST = 0;
  	count = 0;
    end_count=25;
    #(`CYCLE_TIME)      RST = 1;
    #(`CYCLE_TIME*`END_COUNT)	$fclose(handle); $finish;
  end

  //Print result to "CO_P2_Result.txt"
  always@(posedge CLK) begin
    count = count + 1;
  	if( count == `END_COUNT ) begin
      $fdisplay(handle, "r0=%d\nr1=%d\nr2=%d\nr3=%d\nr4=%d\nr5=%d\nr6=%d\nr7=%d\nr8=%d\nr9=%d\nr10=%d\nr11=%d\nr12=%d",
  	      cpu.RF.Reg_File[0], cpu.RF.Reg_File[1], cpu.RF.Reg_File[2], cpu.RF.Reg_File[3], cpu.RF.Reg_File[4],
  			  cpu.RF.Reg_File[5], cpu.RF.Reg_File[6], cpu.RF.Reg_File[7], cpu.RF.Reg_File[8], cpu.RF.Reg_File[9],
  			  cpu.RF.Reg_File[10],cpu.RF.Reg_File[11], cpu.RF.Reg_File[12]
  			  );
  	end
  	else ;
  end

endmodule

CO_Lab_1/code/Single_Cycle_CPU.vcd
$date
	Mon Jul  9 13:45:26 2018
$end
$version
	Icarus Verilog
$end
$timescale
	1s
$end
$scope module TestBench $end
$var reg 1 ! CLK $end
$var reg 1 " RST $end
$var integer 32 # count [31:0] $end
$var integer 32 $ end_count [31:0] $end
$var integer 32 % handle [31:0] $end
$scope module cpu $end
$var wire 1 & clk_i $end
$var wire 1 ' rst_i $end
$scope module PC $end
$var wire 1 ( clk_i $end
$var wire 32 ) pc_in_i [31:0] $end
$var wire 1 * rst_i $end
$var reg 32 + pc_out_o [31:0] $end
$upscope $end
$scope module Adder1 $end
$var wire 32 , src1_i [31:0] $end
$var wire 32 - src2_i [31:0] $end
$var wire 32 . sum_o [31:0] $end
$upscope $end
$scope module IM $end
$var wire 32 / pc_addr_i [31:0] $end
$var integer 32 0 i [31:0] $end
$var reg 32 1 instr_o [31:0] $end
$upscope $end
$scope module Mux_Write_Reg $end
$var wire 5 2 data0_i [4:0] $end
$var wire 5 3 data1_i [4:0] $end
$var wire 1 4 select_i $end
$var reg 5 5 data_o [4:0] $end
$upscope $end
$scope module RF $end
$var wire 5 6 RDaddr_i [4:0] $end
$var wire 32 7 RDdata_i [31:0] $end
$var wire 5 8 RSaddr_i [4:0] $end
$var wire 32 9 RSdata_o [31:0] $end
$var wire 5 : RTaddr_i [4:0] $end
$var wire 32 ; RTdata_o [31:0] $end
$var wire 1 < RegWrite_i $end
$var wire 1 = clk_i $end
$var wire 1 > rst_i $end
$upscope $end
$scope module Decoder $end
$var wire 6 ? instr_op_i [5:0] $end
$var reg 1 @ ALUSrc_o $end
$var reg 3 A ALU_op_o [2:0] $end
$var reg 1 B Branch_o $end
$var reg 1 C RegDst_o $end
$var reg 1 D RegWrite_o $end
$upscope $end
$scope module AC $end
$var wire 3 E ALUOp_i [2:0] $end
$var wire 6 F funct_i [5:0] $end
$var reg 4 G ALUCtrl_o [3:0] $end
$upscope $end
$scope module SE $end
$var wire 16 H data_i [15:0] $end
$var reg 32 I data_o [31:0] $end
$upscope $end
$scope module Mux_ALUSrc $end
$var wire 32 J data0_i [31:0] $end
$var wire 32 K data1_i [31:0] $end
$var wire 1 L select_i $end
$var reg 32 M data_o [31:0] $end
$upscope $end
$scope module ALU $end
$var wire 4 N ctrl_i [3:0] $end
$var wire 32 O src1_i [31:0] $end
$var wire 32 P src2_i [31:0] $end
$var wire 1 Q zero_o $end
$var reg 32 R result_o [31:0] $end
$upscope $end
$scope module Adder2 $end
$var wire 32 S src1_i [31:0] $end
$var wire 32 T src2_i [31:0] $end
$var wire 32 U sum_o [31:0] $end
$upscope $end
$scope module Shifter $end
$var wire 32 V data_i [31:0] $end
$var wire 32 W data_o [31:0] $end
$upscope $end
$scope module Mux_PC_Source $end
$var wire 32 X data0_i [31:0] $end
$var wire 32 Y data1_i [31:0] $end
$var wire 1 Z select_i $end
$var reg 32 [ data_o [31:0] $end
$upscope $end
$upscope $end
$upscope $end
$enddefinitions $end
#0
$dumpvars
bx [
zZ
bz Y
bz X
bz W
bz V
bz U
bz T
bz S
bx R
zQ
bz P
bz O
bz N
bx M
zL
bz K
bz J
bx I
bz H
bx G
bz F
bz E
xD
xC
xB
bx A
x@
bz ?
z>
z=
z<
bx ;
bz :
bx 9
bz 8
bz 7
bz 6
bx 5
z4
bz 3
bz 2
bx 1
b100000 0
bz /
bz .
bz -
bz ,
bx +
z*
bz )
z(
0'
0&
b10 %
b11001 $
b0 #
0"
0!
$end
#5
b1 #
1!
1&
#10
0!
0&
1"
1'
#15
b10 #
1!
1&
#20
0!
0&
#25
b11 #
1!
1&
#30
0!
0&
#35
b100 #
1!
1&
#40
0!
0&
#45
b101 #
1!
1&
#50
0!
0&
#55
b110 #
1!
1&
#60
0!
0&
#65
b111 #
1!
1&
#70
0!
0&
#75
b1000 #
1!
1&
#80
0!
0&
#85
b1001 #
1!
1&
#90
0!
0&
#95
b1010 #
1!
1&
#100
0!
0&
#105
b1011 #
1!
1&
#110
0!
0&
#115
b1100 #
1!
1&
#120
0!
0&
#125
b1101 #
1!
1&
#130
0!
0&
#135
b1110 #
1!
1&
#140
0!
0&
#145
b1111 #
1!
1&
#150
0!
0&
#155
b10000 #
1!
1&
#160
0!
0&
#165
b10001 #
1!
1&
#170
0!
0&
#175
b10010 #
1!
1&
#180
0!
0&
#185
b10011 #
1!
1&
#190
0!
0&
#195
b10100 #
1!
1&
#200
0!
0&
#205
b10101 #
1!
1&
#210
0!
0&
#215
b10110 #
1!
1&
#220
0!
0&
#225
b10111 #
1!
1&
#230
0!
0&
#235
b11000 #
1!
1&
#240
0!
0&
#245
b11001 #
1!
1&
#250
0!
0&
#255
b11010 #
1!
1&
