CO_Lab_1/code/MUX_2to1.v
//Subject:     CO project 1 - MUX 221
//--------------------------------------------------------------------------------
//Version:     1
//--------------------------------------------------------------------------------
//Writer:      Yu-Chen Hsiao
//----------------------------------------------
//Date:         2018/7/19
//----------------------------------------------
//Description:  Multiplexer
//--------------------------------------------------------------------------------

module MUX_2to1(data0_i, data1_i, select_i, data_o);

  parameter size = 0;

  //I/O ports
  input   [size-1:0] data0_i;
  input   [size-1:0] data1_i;
  input              select_i;
  output  [size-1:0] data_o;

  //Internal Signals
  wire    data0_i;
  wire    data1_i;
  wire    select_i;
  wire    data_o;

  //Main function
  assign data_o = (select_i == 0) ? data0_i : data1_i;

endmodule

CO_Lab_1/code/Shift_Left_Two_32.v
//Subject:      CO project 1 - Shift_Left_Two_32
//--------------------------------------------------------------------------------
//Version:     1
//--------------------------------------------------------------------------------
//Description: 
//--------------------------------------------------------------------------------

module Shift_Left_Two_32(
    data_i,
    data_o
    );

//I/O ports                    
input [32-1:0] data_i;
output [32-1:0] data_o;

//shift left 2
     
endmodule

CO_Lab_1/code/Adder.v
//Subject:     CO project 1 - Adder
//--------------------------------------------------------------------------------
//Version:     1
//--------------------------------------------------------------------------------
//Writer:Yu-Chen Hsiao
//----------------------------------------------
//Date:2018/7/10
//----------------------------------------------
//Description:Adder Operation
//--------------------------------------------------------------------------------

module Adder(src1_i, src2_i, sum_o);
  //I/O ports
  input  [32-1:0]  src1_i;
  input  [32-1:0]	 src2_i;
  output [32-1:0]	 sum_o;

  //Internal Signals
  wire   [32-1:0]	 sum_o;

  //Main function
  assign sum_o = src1_i + src2_i;
endmodule

CO_Lab_1/code/ALU.v
//Subject:     CO project 1 - ALU
//--------------------------------------------------------------------------------
//Version:     1
//--------------------------------------------------------------------------------
//Writer:Yu-Chen Hsiao
//----------------------------------------------
//Date:2018/7/11
//----------------------------------------------
//Description:ALU Operation
//--------------------------------------------------------------------------------

module ALU(src1_i, src2_i, ctrl_i, shamt_i, result_o, zero_o);

  //I/O ports
  input  [32-1:0]  src1_i;
  input  [32-1:0]	 src2_i;
  input  [4-1:0]   ctrl_i;
  input  [5-1:0]   shamt_i;

  output [32-1:0]	 result_o;
  output           zero_o;

  //Internal signals
  wire signed [32-1:0]  result_o;
  wire                  zero_o;
  wire                  isEqual;

  //Parameter

  //Main function
  assign result_o = (ctrl_i == 4'b0001) ? src1_i + src2_i  :
                    (ctrl_i == 4'b0010) ? src1_i - src2_i  :
                    (ctrl_i == 4'b0011) ? src1_i & src2_i  :
                    (ctrl_i == 4'b0100) ? src1_i | src2_i  :
                    (ctrl_i == 4'b0101) ? ((src1_i < src2_i) ? 32'd1 : 32'd0) :
                    (ctrl_i == 4'b0110) ? src2_i >> shamt_i:  // sra
                    (ctrl_i == 4'b0111) ? src1_i >> src2_i :  // srav
                    (ctrl_i == 4'b1010) ? src2_i << 16     :  // lui
                                                    0      ;  // default
  assign zero_o = (ctrl_i == 4'b1000) ? ((src1_i == src2_i) ? 1'b1 : 1'b0) :
                  (ctrl_i == 4'b1001) ? ((src1_i == src2_i) ? 1'b0 : 1'b1) :
                                                              1'b0 ;  // default
  // always @ (ctrl_i) begin
  //   case (ctrl_i)
  //     1  : result_o <= src1_i + src2_i;            // addu, addi
  //     2  : result_o <= src1_i - src2_i;            // sub
  //     3  : result_o <= src1_i & src2_i;            // AND
  //     4  : result_o <= src1_i | src2_i;            // OR
  //     5  : result_o <= (src1_i < src2_i) ? 32'd1 : 32'd0;  // slt, sltiu
  //     6  : result_o <= src1_i >> src2_i;
  //     10 : result_o <= src2_i << 16;
  //     default : result_o <= 32'd0;// default
  //   endcase
  //   case (ctrl_i)
  //     8  : zero_o <= (src1_i == src2_i) ? 1'b1 : 1'b0;
  //     9  : zero_o <= (src1_i == src2_i) ? 1'b0 : 1'b1;
  //     default : zero_o <= 1'b0;
  //   endcase
  // end
endmodule

CO_Lab_1/code/Sign_Extend.v
//Subject:     CO project 1 - Sign extend
//--------------------------------------------------------------------------------
//Version:     1
//--------------------------------------------------------------------------------
//Writer:       Yu-Chien Hsiao
//----------------------------------------------
//Date:         2018/7/19
//----------------------------------------------
//Description:  finish
//--------------------------------------------------------------------------------

module Sign_Extend(
    data_i,
    data_o
    );

//I/O ports
input   [16-1:0] data_i;
output  [32-1:0] data_o;

//Internal Signals
reg     [32-1:0] data_o;

//Sign extended
always @ (data_i) begin
  data_o[16-1:0] = data_i;
  data_o[32-1:16] = {16{data_i[16-1]}};
end

endmodule

CO_Lab_1/code/ALU_Ctrl.v
//Subject:     CO project 1 - ALU Controller
//--------------------------------------------------------------------------------
//Version:     1
//--------------------------------------------------------------------------------
//Writer:      Yu-Chien Hsiao
//----------------------------------------------
//Date:        2018/7/19
//----------------------------------------------
//Description:
//--------------------------------------------------------------------------------

module ALU_Ctrl(funct_i, ALUOp_i, ALUCtrl_o);

  //I/O ports
  input      [6-1:0] funct_i;
  input      [3-1:0] ALUOp_i;

  output     [4-1:0] ALUCtrl_o;

  //Internal Signals
  wire       [4-1:0] ALUCtrl_o;

  //Parameter


  //Select exact operation
  assign ALUCtrl_o = ({ALUOp_i,funct_i} == 9'b000_100001 | ALUOp_i == 3'b001)
                                                        ? 4'b0001 :  // 1.addu,addi
                   ({ALUOp_i,funct_i} == 9'b000_100011) ? 4'b0010 :  // 2.sub
                   ({ALUOp_i,funct_i} == 9'b000_100100) ? 4'b0011 :  // 3.AND
                   ({ALUOp_i,funct_i} == 9'b000_100101 | ALUOp_i == 3'b110)
                                                        ? 4'b0100 :  // 4.OR,ORi
                   ({ALUOp_i,funct_i} == 9'b000_101010 | ALUOp_i == 3'b010)
                                                        ? 4'b0101 :  // 5.slt,sltiu
                   ({ALUOp_i,funct_i} == 9'b000_000011) ? 4'b0110 :  // 6.sra
                   ({ALUOp_i,funct_i} == 9'b000_000111) ? 4'b0111 :  // 7.srav
                    (ALUOp_i == 3'b011)                 ? 4'b1000 :  // 8.beq
                    (ALUOp_i == 3'b100)                 ? 4'b1001 :  // 9.bnq
                    (ALUOp_i == 3'b101)                 ? 4'b1010 :  // 10.lui
                                                          4'b0000 ;  // 0.default

endmodule

CO_Lab_1/code/Decoder.v
//Subject:     CO project 1 - Decoder
//--------------------------------------------------------------------------------
//Version:     1
//--------------------------------------------------------------------------------
//Writer:
//----------------------------------------------
//Date:
//----------------------------------------------
//Description:
//--------------------------------------------------------------------------------

module Decoder(instr_op_i, RegWrite_o, ALU_op_o, ALUSrc_o, RegDst_o);

  //I/O ports
  input  [6-1:0] instr_op_i;

  output         RegWrite_o;
  output [3-1:0] ALU_op_o;
  output         ALUSrc_o;
  output         RegDst_o;

  //Internal Signals
  wire           RegWrite_o;
  wire   [3-1:0] ALU_op_o;
  wire           ALUSrc_o;
  wire           RegDst_o;

  //Parameter


  //Main function
  assign ALU_op_o = (instr_op_i==6'b000000) ? 3'b000 :  // 0.R-type
                    (instr_op_i==6'b001000) ? 3'b001 :  // 1.addi
                    (instr_op_i==6'b001011) ? 3'b010 :  // 2.sltiu
                    (instr_op_i==6'b000100) ? 3'b011 :  // 3.beq
                    (instr_op_i==6'b000101) ? 3'b100 :  // 4.bnq
                    (instr_op_i==6'b001111) ? 3'b101 :  // 5.lui
                    (instr_op_i==6'b001101) ? 3'b110 :  // 6.ori
                                              3'b111 ;

  // Don't need to read data: beq, bne
  assign RegWrite_o = (instr_op_i == 6'b000100 | instr_op_i == 6'b000101) ? 0 : 1;
  // Read immediate or offset from register file: lw, sw, *i, beq, bnq, lui
  assign ALUSrc_o = (instr_op_i == 6'b000000 |
                     instr_op_i == 6'b000100 |
                     instr_op_i == 6'b000101) ? 0 : 1;
  // Set Rd(1) or Rt(0) as destination : lw, sw, *i;
  assign RegDst_o = (instr_op_i == 6'b000000) ? 1 : 0;

endmodule

CO_Lab_1/code/Reg_File.v
//Subject:     CO project 1 - Register File
//--------------------------------------------------------------------------------
//Version:     1
//--------------------------------------------------------------------------------
//Writer:
//----------------------------------------------
//Date:
//----------------------------------------------
//Description:
//--------------------------------------------------------------------------------
module Reg_File(
    clk_i,
	  rst_i,
    RSaddr_i,
    RTaddr_i,
    RDaddr_i,
    RDdata_i,
    RegWrite_i,
    RSdata_o,
    RTdata_o
    );

//I/O ports
input           clk_i;
input           rst_i;
input           RegWrite_i;
input  [5-1:0]  RSaddr_i;
input  [5-1:0]  RTaddr_i;
input  [5-1:0]  RDaddr_i;
input  [32-1:0] RDdata_i;

output [32-1:0] RSdata_o;
output [32-1:0] RTdata_o;

//Internal signals/registers
reg  signed [32-1:0] Reg_File [0:32-1];     //32 word registers
wire        [32-1:0] RSdata_o;
wire        [32-1:0] RTdata_o;

//Read the data
assign RSdata_o = Reg_File[RSaddr_i] ;
assign RTdata_o = Reg_File[RTaddr_i] ;

//Writing data when postive edge clk_i and RegWrite_i was set.
always @( posedge rst_i or posedge clk_i  ) begin
    if(rst_i == 0) begin
	    Reg_File[0]  <= 0; Reg_File[1]  <= 0; Reg_File[2]  <= 0; Reg_File[3]  <= 0;
	    Reg_File[4]  <= 0; Reg_File[5]  <= 0; Reg_File[6]  <= 0; Reg_File[7]  <= 0;
      Reg_File[8]  <= 0; Reg_File[9]  <= 0; Reg_File[10] <= 0; Reg_File[11] <= 0;
	    Reg_File[12] <= 0; Reg_File[13] <= 0; Reg_File[14] <= 0; Reg_File[15] <= 0;
      Reg_File[16] <= 0; Reg_File[17] <= 0; Reg_File[18] <= 0; Reg_File[19] <= 0;
      Reg_File[20] <= 0; Reg_File[21] <= 0; Reg_File[22] <= 0; Reg_File[23] <= 0;
      Reg_File[24] <= 0; Reg_File[25] <= 0; Reg_File[26] <= 0; Reg_File[27] <= 0;
      Reg_File[28] <= 0; Reg_File[29] <= 0; Reg_File[30] <= 0; Reg_File[31] <= 0;
	end
    else begin
        if(RegWrite_i)
            Reg_File[RDaddr_i] <= RDdata_i;
    		else
    		    Reg_File[RDaddr_i] <= Reg_File[RDaddr_i];
	end
end

endmodule

CO_Lab_1/code/Instr_Memory.v
//Subject:     CO project 1 - Instruction Memory
//--------------------------------------------------------------------------------
//Version:     1
//--------------------------------------------------------------------------------
//Writer:
//----------------------------------------------
//Date:
//----------------------------------------------
//Description:
//--------------------------------------------------------------------------------

module Instr_Memory(pc_addr_i, instr_o);

	//I/O ports
	input  [32-1:0]  pc_addr_i;
	output [32-1:0]	 instr_o;

	//Internal Signals
	reg    [32-1:0]	 instr_o;
	integer          i;

	//32 words Memory
	reg    [32-1:0]  Instr_Mem [0:32-1];

	//Parameter

	//Main function
	always @(pc_addr_i) begin
		instr_o = Instr_Mem[pc_addr_i/4];
	end

	//Initial Memory Contents
	initial begin
	    for ( i=0; i<32; i=i+1 )
		    Instr_Mem[i] = 32'b0;
	    $readmemb("CO_P1_test_data1.txt", Instr_Mem);  //Read instruction from "CO_P1_test_data1.txt"
	end
endmodule

CO_Lab_1/code/ProgramCounter.v
//Subject:     CO project 1 - PC
//--------------------------------------------------------------------------------
//Version:     1
//--------------------------------------------------------------------------------
//Writer:
//----------------------------------------------
//Date:
//----------------------------------------------
//Description:
//--------------------------------------------------------------------------------

module ProgramCounter(clk_i, rst_i, pc_in_i, pc_out_o);

//I/O ports
input           clk_i;
input	          rst_i;
input  [32-1:0] pc_in_i;
output [32-1:0] pc_out_o;

//Internal Signals
reg    [32-1:0] pc_out_o;

//Parameter


//Main function
always @(posedge clk_i) begin
  if(~rst_i)
	    pc_out_o <= 0;
	else
	    pc_out_o <= pc_in_i;
end

endmodule

CO_Lab_1/code/Simple_Single_CPU.v
//Subject:     CO project 1 - Simple Single CPU
//--------------------------------------------------------------------------------
//Version:     1
//--------------------------------------------------------------------------------
//Writer:
//----------------------------------------------
//Date:
//----------------------------------------------
//Description:
//--------------------------------------------------------------------------------
module Simple_Single_CPU(clk_i,	rst_i);

  //I/O port
  input         clk_i;
  input         rst_i;

  //Internal Signles
  /* Main Datapath */
  wire [32-1:0] instruction;
  wire [32-1:0] readData1;
  wire [32-1:0] readData2;
  wire [32-1:0] ALU_result;

  /* Control */
  wire [3-1:0]  ALU_op;
  wire          RegDst;
  wire          RegWrite;
  wire          ALUSrc;


  /* Program Counter */
  wire [32-1:0] program_pre;
  wire [32-1:0] program_now;
  wire [32-1:0] program_next;

  /* MUX */
  wire  [5-1:0]  writeRegMux;
  wire   [32-1:0] ALUSrcMux;

  //Greate componentes
  ProgramCounter PC(
        .clk_i(clk_i),
  	    .rst_i (rst_i),
  	    .pc_in_i(program_pre),
  	    .pc_out_o(program_now)
  	    );

  Adder Adder1(
        .src1_i(program_now),
  	    .src2_i(32'd4),
  	    .sum_o(program_next)
  	    );

  Instr_Memory IM(
        .pc_addr_i(program_now),
  	    .instr_o(instruction)
  	    );

  MUX_2to1 #(.size(5)) Mux_Write_Reg(
          .data0_i(instruction[20:16]),
          .data1_i(instruction[15:11]),
          .select_i(RegDst),
          .data_o(writeRegMux)
          );

  Reg_File RF(
          .clk_i(clk_i),
  	      .rst_i(rst_i),
          .RSaddr_i(instruction[25:21]),
          .RTaddr_i(instruction[20:16]),
          .RDaddr_i(writeRegMux),
          .RDdata_i(ALU_result),
          .RegWrite_i(RegWrite),
          .RSdata_o(readData1),
          .RTdata_o(readData2)
          );

  Decoder Decoder(
        .instr_op_i(instruction[31:26]),
  	    .RegWrite_o(RegWrite),
  	    .ALU_op_o(ALU_op),
  	    .ALUSrc_o(ALUSrc),
  	    .RegDst_o(RegDst)
  	    );

  ALU_Ctrl AC(
          .funct_i(instruction[5:0]),
          .ALUOp_i(ALU_op),
          .ALUCtrl_o(ALUCtrl)
          );
  wire   [4-1:0]  ALUCtrl;

  Sign_Extend SE(
          .data_i(instruction[15:0]),
          .data_o(signExtend)
          );
  wire   [32-1:0] signExtend;

  MUX_2to1 #(.size(32)) Mux_ALUSrc(
          .data0_i(readData2),
          .data1_i(signExtend),
          .select_i(ALUSrc),
          .data_o(ALUSrcMux)
          );


  ALU ALU(
        .src1_i(readData1),
  	    .src2_i(ALUSrcMux),
  	    .ctrl_i(ALUCtrl),
        .shamt_i(instruction[10:6]),
  	    .result_o(ALU_result),
  		  .zero_o(zero)
  	    );
  wire  zero;

  Adder Adder2(
        .src1_i(program_next),
  	    .src2_i(signExtend_shifted),
  	    .sum_o(program_new)
  	    );
  wire  [32-1:0] program_new;

  Shift_Left_Two_32 Shifter(
          .data_i(signExtend),
          .data_o(signExtend_shifted)
          );
  wire  [32-1:0] signExtend_shifted;

  MUX_2to1 #(.size(32)) Mux_PC_Source(
          .data0_i(program_next),
          .data1_i(program_new),
          .select_i(zero),
          .data_o(program_pre)
          );

endmodule

CO_Lab_1/code/Test_Bench.v
//Subject:     CO project 1 - Test Bench
//--------------------------------------------------------------------------------
//Version:     1
//--------------------------------------------------------------------------------
//Writer:
//----------------------------------------------
//Date:
//----------------------------------------------
//Description:
//--------------------------------------------------------------------------------

`define CYCLE_TIME 10
`define END_COUNT 25
module TestBench;

  //Internal Signals
  reg         CLK;
  reg         RST;
  integer     count;
  integer     handle;
  integer     end_count;
  //Greate tested modle
  Simple_Single_CPU cpu(
      .clk_i(CLK),
  		.rst_i(RST)
  		);

  //Main function

  always #(`CYCLE_TIME/2) CLK = ~CLK;

  initial  begin
  	$dumpfile("Single_Cycle_CPU.vcd");
  	$dumpvars;

    handle = $fopen("CO_P1_Result.txt");
  	CLK = 0;
    RST = 0;
  	count = 0;
    end_count=25;
    #(`CYCLE_TIME)      RST = 1;
    #(`CYCLE_TIME*`END_COUNT)	$fclose(handle); $finish;
  end

  //Print result to "CO_P2_Result.txt"
  always@(posedge CLK) begin
    count = count + 1;
  	if( count == `END_COUNT ) begin
      $fdisplay(handle, "r0=%d\nr1=%d\nr2=%d\nr3=%d\nr4=%d\nr5=%d\nr6=%d\nr7=%d\nr8=%d\nr9=%d\nr10=%d\nr11=%d\nr12=%d",
  	      cpu.RF.Reg_File[0], cpu.RF.Reg_File[1], cpu.RF.Reg_File[2], cpu.RF.Reg_File[3], cpu.RF.Reg_File[4],
  			  cpu.RF.Reg_File[5], cpu.RF.Reg_File[6], cpu.RF.Reg_File[7], cpu.RF.Reg_File[8], cpu.RF.Reg_File[9],
  			  cpu.RF.Reg_File[10],cpu.RF.Reg_File[11], cpu.RF.Reg_File[12]
  			  );
  	end
  	else ;
  end

endmodule

CO_Lab_1/code/Single_Cycle_CPU.vcd
$date
	Sat Jul 28 18:02:40 2018
$end
$version
	Icarus Verilog
$end
$timescale
	1s
$end
$scope module TestBench $end
$var reg 1 ! CLK $end
$var reg 1 " RST $end
$var integer 32 # count [31:0] $end
$var integer 32 $ end_count [31:0] $end
$var integer 32 % handle [31:0] $end
$scope module cpu $end
$var wire 4 & ALUCtrl [3:0] $end
$var wire 1 ' ALUSrc $end
$var wire 32 ( ALUSrcMux [31:0] $end
$var wire 3 ) ALU_op [2:0] $end
$var wire 32 * ALU_result [31:0] $end
$var wire 1 + RegDst $end
$var wire 1 , RegWrite $end
$var wire 1 - clk_i $end
$var wire 32 . instruction [31:0] $end
$var wire 32 / program_new [31:0] $end
$var wire 32 0 program_next [31:0] $end
$var wire 32 1 program_now [31:0] $end
$var wire 32 2 program_pre [31:0] $end
$var wire 32 3 readData1 [31:0] $end
$var wire 32 4 readData2 [31:0] $end
$var wire 1 5 rst_i $end
$var wire 32 6 signExtend [31:0] $end
$var wire 32 7 signExtend_shifted [31:0] $end
$var wire 5 8 writeRegMux [4:0] $end
$var wire 1 9 zero $end
$scope module PC $end
$var wire 1 - clk_i $end
$var wire 32 : pc_in_i [31:0] $end
$var wire 1 5 rst_i $end
$var reg 32 ; pc_out_o [31:0] $end
$upscope $end
$scope module Adder1 $end
$var wire 32 < src1_i [31:0] $end
$var wire 32 = src2_i [31:0] $end
$var wire 32 > sum_o [31:0] $end
$upscope $end
$scope module IM $end
$var wire 32 ? pc_addr_i [31:0] $end
$var integer 32 @ i [31:0] $end
$var reg 32 A instr_o [31:0] $end
$upscope $end
$scope module Mux_Write_Reg $end
$var wire 5 B data0_i [4:0] $end
$var wire 5 C data1_i [4:0] $end
$var wire 5 D data_o [4:0] $end
$var wire 1 + select_i $end
$upscope $end
$scope module RF $end
$var wire 5 E RDaddr_i [4:0] $end
$var wire 32 F RDdata_i [31:0] $end
$var wire 5 G RSaddr_i [4:0] $end
$var wire 32 H RSdata_o [31:0] $end
$var wire 5 I RTaddr_i [4:0] $end
$var wire 32 J RTdata_o [31:0] $end
$var wire 1 , RegWrite_i $end
$var wire 1 - clk_i $end
$var wire 1 5 rst_i $end
$upscope $end
$scope module Decoder $end
$var wire 1 ' ALUSrc_o $end
$var wire 3 K ALU_op_o [2:0] $end
$var wire 1 + RegDst_o $end
$var wire 1 , RegWrite_o $end
$var wire 6 L instr_op_i [5:0] $end
$upscope $end
$scope module AC $end
$var wire 4 M ALUCtrl_o [3:0] $end
$var wire 3 N ALUOp_i [2:0] $end
$var wire 6 O funct_i [5:0] $end
$upscope $end
$scope module SE $end
$var wire 16 P data_i [15:0] $end
$var reg 32 Q data_o [31:0] $end
$upscope $end
$scope module Mux_ALUSrc $end
$var wire 32 R data0_i [31:0] $end
$var wire 32 S data1_i [31:0] $end
$var wire 32 T data_o [31:0] $end
$var wire 1 ' select_i $end
$upscope $end
$scope module ALU $end
$var wire 4 U ctrl_i [3:0] $end
$var wire 32 V result_o [31:0] $end
$var wire 5 W shamt_i [4:0] $end
$var wire 32 X src1_i [31:0] $end
$var wire 32 Y src2_i [31:0] $end
$var wire 1 9 zero_o $end
$upscope $end
$scope module Adder2 $end
$var wire 32 Z src1_i [31:0] $end
$var wire 32 [ src2_i [31:0] $end
$var wire 32 \ sum_o [31:0] $end
$upscope $end
$scope module Shifter $end
$var wire 32 ] data_i [31:0] $end
$var wire 32 ^ data_o [31:0] $end
$upscope $end
$scope module Mux_PC_Source $end
$var wire 32 _ data0_i [31:0] $end
$var wire 32 ` data1_i [31:0] $end
$var wire 32 a data_o [31:0] $end
$var wire 1 9 select_i $end
$upscope $end
$upscope $end
$upscope $end
$enddefinitions $end
#0
$dumpvars
bx a
bx `
bx _
bx00 ^
bx ]
bx \
bx00 [
bx Z
bx Y
bx X
bx W
bx V
bx U
bx T
bx S
bx R
bx Q
bx P
bx O
bx N
bx M
bx L
bx K
bx J
bx I
bx H
bx G
bx F
bx E
bx D
bx C
bx B
bx A
b100000 @
bx ?
bx >
b100 =
bx <
bx ;
bx :
x9
bx 8
bx00 7
bx 6
05
bx 4
bx 3
bx 2
bx 1
bx 0
bx /
bx .
0-
x,
x+
bx *
bx )
bx (
x'
bx &
b10 %
b11001 $
b0 #
0"
0!
$end
#5
b1101 *
b1101 F
b1101 V
b100 2
b100 :
b100 a
09
1'
b1101 (
b1101 T
b1101 Y
b111000 /
b111000 \
b111000 `
b110100 7
b110100 [
b110100 ^
b1 &
b1 M
b1 U
1,
b1101 Q
b1101 6
b1101 S
b1101 ]
b1 )
b1 K
b1 N
0+
b1 8
b1 D
b1 E
b0 W
b1101 P
b1101 O
b1000 L
b1 I
b0 4
b0 J
b0 R
b0 G
b0 3
b0 H
b0 X
b0 C
b1 B
b100000000000010000000000001101 A
b100000000000010000000000001101 .
b0 ;
b100 0
b100 >
b100 Z
b100 _
b0 1
b0 <
b0 ?
b1 #
1!
1-
#10
b1101 4
b1101 J
b1101 R
0!
0-
1"
15
#15
b111 *
b111 F
b111 V
b111 (
b111 T
b111 Y
b11100 7
b11100 [
b11100 ^
b111 Q
b111 6
b111 S
b111 ]
b10 8
b10 D
b10 E
b111 P
b111 O
b10 I
b0 4
b0 J
b0 R
b10 B
b1000 2
b1000 :
b1000 a
b100000000000100000000000000111 A
b100000000000100000000000000111 .
b100 ;
b100100 /
b100100 \
b100100 `
b1000 0
b1000 >
b1000 Z
b1000 _
b100 1
b100 <
b100 ?
b10 #
1!
1-
#20
0!
0-
#25
b101 &
b101 M
b101 U
b11111111111111111111111111111111 (
b11111111111111111111111111111111 T
b11111111111111111111111111111111 Y
b11111111111111111111111111111100 7
b11111111111111111111111111111100 [
b11111111111111111111111111111100 ^
b10 )
b10 K
b10 N
b1 *
b1 F
b1 V
b11111111111111111111111111111111 Q
b11111111111111111111111111111111 6
b11111111111111111111111111111111 S
b11111111111111111111111111111111 ]
b11 8
b11 D
b11 E
b11111 W
b1111111111111111 P
b111111 O
b1011 L
b11 I
b1 G
b1101 3
b1101 H
b1101 X
b11111 C
b11 B
b1100 2
b1100 :
b1100 a
b101100001000111111111111111111 A
b101100001000111111111111111111 .
b0 4
b0 J
b0 R
b1000 ;
b1000 /
b1000 \
b1000 `
b1100 0
b1100 >
b1100 Z
b1100 _
b1000 1
b1000 <
b1000 ?
b11 #
1!
1-
#30
0!
0-
#35
b0 *
b0 F
b0 V
b1000 &
b1000 M
b1000 U
b11 )
b11 K
b11 N
0'
b0 (
b0 T
b0 Y
b100 7
b100 [
b100 ^
0,
b1 Q
b1 6
b1 S
b1 ]
b0 8
b0 D
b0 E
b0 W
b1 P
b1 O
b100 L
b0 I
b11 G
b1 3
b1 H
b1 X
b0 C
b0 B
b10000 2
b10000 :
b10000 a
b10000011000000000000000000001 A
b10000011000000000000000000001 .
b0 4
b0 J
b0 R
b1100 ;
b10100 /
b10100 \
b10100 `
b10000 0
b10000 >
b10000 Z
b10000 _
b1100 1
b1100 <
b1100 ?
b100 #
1!
1-
#40
0!
0-
#45
b1 *
b1 F
b1 V
b101 &
b101 M
b101 U
b1000000010101000 7
b1000000010101000 [
b1000000010101000 ^
1,
b10000000101010 Q
b10000000101010 6
b10000000101010 S
b10000000101010 ]
b0 )
b0 K
b0 N
1+
b1101 (
b1101 T
b1101 Y
b100 8
b100 D
b100 E
b10000000101010 P
b101010 O
b0 L
b1 I
b1101 4
b1101 J
b1101 R
b10 G
b111 3
b111 H
b111 X
b100 C
b1 B
b10100 2
b10100 :
b10100 a
b10000010010000000101010 A
b10000010010000000101010 .
b10000 ;
b1000000010111100 /
b1000000010111100 \
b1000000010111100 `
b10100 0
b10100 >
b10100 Z
b10100 _
b10000 1
b10000 <
b10000 ?
b101 #
1!
1-
#50
0!
0-
#55
b11 &
b11 M
b11 U
b1010000010010000 7
b1010000010010000 [
b1010000010010000 ^
b10100000100100 Q
b10100000100100 6
b10100000100100 S
b10100000100100 ]
b1 (
b1 T
b1 Y
b101 8
b101 D
b101 E
b10100000100100 P
b100100 O
b100 I
b1 4
b1 J
b1 R
b1 G
b1101 3
b1101 H
b1101 X
b101 C
b100 B
b11000 2
b11000 :
b11000 a
b1001000010100000100100 A
b1001000010100000100100 .
b10100 ;
b1010000010101000 /
b1010000010101000 \
b1010000010101000 `
b11000 0
b11000 >
b11000 Z
b11000 _
b10100 1
b10100 <
b10100 ?
b110 #
1!
1-
#60
0!
0-
#65
b1100 *
b1100 F
b1100 V
b1000000010001100 7
b1000000010001100 [
b1000000010001100 ^
b10 &
b10 M
b10 U
b10000000100011 Q
b10000000100011 6
b10000000100011 S
b10000000100011 ]
b100 8
b100 D
b100 E
b10000000100011 P
b100011 O
b101 I
b100 C
b101 B
b11100 2
b11100 :
b11100 a
b1001010010000000100011 A
b1001010010000000100011 .
b11000 ;
b1000000010101000 /
b1000000010101000 \
b1000000010101000 `
b11100 0
b11100 >
b11100 Z
b11100 _
b11000 1
b11000 <
b11000 ?
b111 #
1!
1-
#70
0!
0-
#75
b0 *
b0 F
b0 V
b0 7
b0 [
b0 ^
b0 &
b0 M
b0 U
b0 Q
b0 6
b0 S
b0 ]
b0 (
b0 T
b0 Y
b0 8
b0 D
b0 E
b0 P
b0 O
b0 I
b0 4
b0 J
b0 R
b0 G
b0 3
b0 H
b0 X
b0 C
b0 B
b100000 2
b100000 :
b100000 a
b0 A
b0 .
b11100 ;
b100000 /
b100000 \
b100000 `
b100000 0
b100000 >
b100000 Z
b100000 _
b11100 1
b11100 <
b11100 ?
b1000 #
1!
1-
#80
0!
0-
#85
b100100 2
b100100 :
b100100 a
b100000 ;
b100100 /
b100100 \
b100100 `
b100100 0
b100100 >
b100100 Z
b100100 _
b100000 1
b100000 <
b100000 ?
b1001 #
1!
1-
#90
0!
0-
#95
b101000 2
b101000 :
b101000 a
b100100 ;
b101000 /
b101000 \
b101000 `
b101000 0
b101000 >
b101000 Z
b101000 _
b100100 1
b100100 <
b100100 ?
b1010 #
1!
1-
#100
0!
0-
#105
b101100 2
b101100 :
b101100 a
b101000 ;
b101100 /
b101100 \
b101100 `
b101100 0
b101100 >
b101100 Z
b101100 _
b101000 1
b101000 <
b101000 ?
b1011 #
1!
1-
#110
0!
0-
#115
b110000 2
b110000 :
b110000 a
b101100 ;
b110000 /
b110000 \
b110000 `
b110000 0
b110000 >
b110000 Z
b110000 _
b101100 1
b101100 <
b101100 ?
b1100 #
1!
1-
#120
0!
0-
#125
b110100 2
b110100 :
b110100 a
b110000 ;
b110100 /
b110100 \
b110100 `
b110100 0
b110100 >
b110100 Z
b110100 _
b110000 1
b110000 <
b110000 ?
b1101 #
1!
1-
#130
0!
0-
#135
b111000 2
b111000 :
b111000 a
b110100 ;
b111000 /
b111000 \
b111000 `
b111000 0
b111000 >
b111000 Z
b111000 _
b110100 1
b110100 <
b110100 ?
b1110 #
1!
1-
#140
0!
0-
#145
b111100 2
b111100 :
b111100 a
b111000 ;
b111100 /
b111100 \
b111100 `
b111100 0
b111100 >
b111100 Z
b111100 _
b111000 1
b111000 <
b111000 ?
b1111 #
1!
1-
#150
0!
0-
#155
b1000000 2
b1000000 :
b1000000 a
b111100 ;
b1000000 /
b1000000 \
b1000000 `
b1000000 0
b1000000 >
b1000000 Z
b1000000 _
b111100 1
b111100 <
b111100 ?
b10000 #
1!
1-
#160
0!
0-
#165
b1000100 2
b1000100 :
b1000100 a
b1000000 ;
b1000100 /
b1000100 \
b1000100 `
b1000100 0
b1000100 >
b1000100 Z
b1000100 _
b1000000 1
b1000000 <
b1000000 ?
b10001 #
1!
1-
#170
0!
0-
#175
b1001000 2
b1001000 :
b1001000 a
b1000100 ;
b1001000 /
b1001000 \
b1001000 `
b1001000 0
b1001000 >
b1001000 Z
b1001000 _
b1000100 1
b1000100 <
b1000100 ?
b10010 #
1!
1-
#180
0!
0-
#185
b1001100 2
b1001100 :
b1001100 a
b1001000 ;
b1001100 /
b1001100 \
b1001100 `
b1001100 0
b1001100 >
b1001100 Z
b1001100 _
b1001000 1
b1001000 <
b1001000 ?
b10011 #
1!
1-
#190
0!
0-
#195
b1010000 2
b1010000 :
b1010000 a
b1001100 ;
b1010000 /
b1010000 \
b1010000 `
b1010000 0
b1010000 >
b1010000 Z
b1010000 _
b1001100 1
b1001100 <
b1001100 ?
b10100 #
1!
1-
#200
0!
0-
#205
b1010100 2
b1010100 :
b1010100 a
b1010000 ;
b1010100 /
b1010100 \
b1010100 `
b1010100 0
b1010100 >
b1010100 Z
b1010100 _
b1010000 1
b1010000 <
b1010000 ?
b10101 #
1!
1-
#210
0!
0-
#215
b1011000 2
b1011000 :
b1011000 a
b1010100 ;
b1011000 /
b1011000 \
b1011000 `
b1011000 0
b1011000 >
b1011000 Z
b1011000 _
b1010100 1
b1010100 <
b1010100 ?
b10110 #
1!
1-
#220
0!
0-
#225
b1011100 2
b1011100 :
b1011100 a
b1011000 ;
b1011100 /
b1011100 \
b1011100 `
b1011100 0
b1011100 >
b1011100 Z
b1011100 _
b1011000 1
b1011000 <
b1011000 ?
b10111 #
1!
1-
#230
0!
0-
#235
b1100000 2
b1100000 :
b1100000 a
b1011100 ;
b1100000 /
b1100000 \
b1100000 `
b1100000 0
b1100000 >
b1100000 Z
b1100000 _
b1011100 1
b1011100 <
b1011100 ?
b11000 #
1!
1-
#240
0!
0-
